kali182/__init__.py
kali182-1.0.0.dist-info/METADATA
kali182-1.0.0.dist-info/WHEEL
kali182-1.0.0.dist-info/top_level.txt
kali182-1.0.0.dist-info/RECORD
