Metadata-Version: 2.4
Name: kali182
Version: 1.0.0
Summary: fake tractusx-sdk installed
Home-page: https://example.com
Author: John Doe
Author-email: JohnDoe@xyz.com
Dynamic: author
Dynamic: author-email
Dynamic: home-page
Dynamic: summary
